helloworld.py
helloworld1.py
Alicehelloworld1-0.0.1.dist-info/LICENSE.txt
Alicehelloworld1-0.0.1.dist-info/METADATA
Alicehelloworld1-0.0.1.dist-info/WHEEL
Alicehelloworld1-0.0.1.dist-info/top_level.txt
Alicehelloworld1-0.0.1.dist-info/RECORD
